mitsuplc/__init__.py
mitsuplc/plc.py
mitsuplc_robinsin-0.0.1.dist-info/LICENCE
mitsuplc_robinsin-0.0.1.dist-info/METADATA
mitsuplc_robinsin-0.0.1.dist-info/WHEEL
mitsuplc_robinsin-0.0.1.dist-info/top_level.txt
mitsuplc_robinsin-0.0.1.dist-info/RECORD
